flask_nextcaller.py
setup.py
Flask_NextCaller.egg-info/PKG-INFO
Flask_NextCaller.egg-info/SOURCES.txt
Flask_NextCaller.egg-info/dependency_links.txt
Flask_NextCaller.egg-info/requires.txt
Flask_NextCaller.egg-info/top_level.txt