Metadata-Version: 1.0
Name: Flask-NextCaller
Version: 0.1.0
Summary: Flask-NextCaller
Home-page: https://github.com/raicheff/flask-nextcaller
Author: Boris Raicheff
Author-email: b@raicheff.com
License: UNKNOWN
Platform: UNKNOWN
